{"stats":{"minecraft:custom":{"minecraft:time_since_rest":121187,"minecraft:open_chest":15,"minecraft:crouch_one_cm":152,"minecraft:sprint_one_cm":27421,"minecraft:play_time":121187,"minecraft:walk_one_cm":199711,"minecraft:sneak_time":2573,"minecraft:walk_under_water_one_cm":477,"minecraft:mob_kills":1,"minecraft:jump":67,"minecraft:minecart_one_cm":1770972,"minecraft:damage_dealt":10,"minecraft:leave_game":14,"minecraft:walk_on_water_one_cm":8,"minecraft:time_since_death":121187,"minecraft:total_world_time":121187,"minecraft:fly_one_cm":665075},"minecraft:picked_up":{"minecraft:torch":1,"minecraft:lever":1,"minecraft:powered_rail":2,"minecraft:minecart":4,"minecraft:rail":1},"minecraft:used":{"minecraft:lever":252,"minecraft:rail":1303,"minecraft:lantern":189,"minecraft:powered_rail":248,"minecraft:minecart":28,"minecraft:chest":2,"minecraft:stone":1522,"minecraft:redstone_block":3}},"DataVersion":3578}